courses/__init__.py
courses/admin.py
courses/apps.py
courses/forms.py
courses/models.py
courses/settings.py
courses/urls.py
courses/utils.py
courses/validators.py
courses/views.py
courses/views_ajax.py
courses/locale/sk/LC_MESSAGES/django.mo
courses/locale/sk/LC_MESSAGES/django.po
courses/management/__init__.py
courses/management/commands/__init__.py
courses/management/commands/notify-run-start.py
courses/migrations/0001_initial.py
courses/migrations/__init__.py
courses/static/courses/js/video_tracking.js
courses/templates/courses/chapter_detail.html
courses/templates/courses/chapter_submission.html
courses/templates/courses/course_detail.html
courses/templates/courses/courses_list.html
courses/templates/courses/lecture_detail.html
courses/templates/courses/run_detail.html
courses/templates/courses/runs_list.html
courses/templates/courses/emails/run_start_email_body.txt
courses/templates/courses/emails/run_start_email_subject.txt
courses/templates/courses/emails/subscribed_email_body.txt
courses/templates/courses/emails/subscribed_email_subject.txt
courses/templates/courses/includes/breadcrumbs.html
courses/templates/courses/includes/chapter_detail_header.html
courses/templates/courses/includes/course_detail_header.html
courses/templates/courses/includes/course_run_detail.html
courses/templates/courses/includes/courses_runs_list.html
courses/templates/courses/includes/modal_subscribe.html
courses/templates/courses/includes/submission.html
courses/templatetags/__init__.py
courses/templatetags/courses_extra.py
courses/tests/__init__.py
courses/tests/test_models.py
courses/tests/test_views.py
django_courses-1.0a0.dist-info/LICENSE
django_courses-1.0a0.dist-info/METADATA
django_courses-1.0a0.dist-info/WHEEL
django_courses-1.0a0.dist-info/top_level.txt
django_courses-1.0a0.dist-info/RECORD
