Metadata-Version: 2.1
Name: django-courses
Version: 1.0a0
Summary: Courses is a simple Django app to manage online courses (education).
Home-page: https://github.com/vault19/django-courses
Author: Vault19 o.z.
License: MIT License
Platform: UNKNOWN
Classifier: Environment :: Web Environment
Classifier: Framework :: Django
Classifier: Framework :: Django :: 2.2
Classifier: Framework :: Django :: 3.1
Classifier: Framework :: Django :: 3.2
Classifier: Intended Audience :: Developers
Classifier: License :: OSI Approved :: MIT License
Classifier: Operating System :: OS Independent
Classifier: Programming Language :: Python
Classifier: Programming Language :: Python :: 3.7
Classifier: Programming Language :: Python :: 3.8
Classifier: Programming Language :: Python :: 3.9
Classifier: Topic :: Internet :: WWW/HTTP
Classifier: Topic :: Internet :: WWW/HTTP :: Dynamic Content
Requires-Dist: django
Requires-Dist: django-autoslug
Requires-Dist: django-bootstrap-v5
Requires-Dist: django-embed-video
Requires-Dist: django-markdownify
